automatilib/__init__.py
automatilib/cola/__init__.py
automatilib/cola/apps.py
automatilib/cola/backend.py
automatilib/cola/urls.py
automatilib/cola/views.py
automatilib/core/__init__.py
automatilib/core/apps.py
automatilib/core/models.py
automatilib-1.2.1.dist-info/LICENSE
automatilib-1.2.1.dist-info/METADATA
automatilib-1.2.1.dist-info/WHEEL
automatilib-1.2.1.dist-info/RECORD
