Metadata-Version: 2.1
Name: automatilib
Version: 1.2.1
Summary: Automatilib is common django code used by the i.AI team.
License: MIT
Author: i.AI
Author-email: i-dot-ai-team@cabinetoffice.gov.uk
Maintainer: i.AI
Maintainer-email: i-dot-ai-team@cabinetoffice.gov.uk
Requires-Python: >=3.9,<4.0
Classifier: Development Status :: 2 - Pre-Alpha
Classifier: Environment :: Web Environment
Classifier: Framework :: Django
Classifier: Framework :: Django :: 4.2
Classifier: Intended Audience :: Developers
Classifier: License :: OSI Approved :: MIT License
Classifier: Operating System :: OS Independent
Classifier: Programming Language :: Python
Classifier: Programming Language :: Python :: 3
Classifier: Programming Language :: Python :: 3.9
Classifier: Programming Language :: Python :: 3.10
Classifier: Programming Language :: Python :: 3.11
Classifier: Programming Language :: Python :: 3.12
Requires-Dist: django (>=4.2.7,<5.0.0)
Requires-Dist: django-use-email-as-username (>=1.4.0,<2.0.0)
Requires-Dist: python-jose[cryptography] (>=3.3.0,<4.0.0)
Requires-Dist: requests (>=2.31.0,<3.0.0)
